<?xml version="1.0" encoding="UTF-8"?>
<level>
    <arbalest x="200" y="545" ></arbalest>
    <bird x="400" y="696" type="Red" ></bird>
    <bird x="450" y="696" type="Red" ></bird>
    <bird x="500" y="696" type="Red" ></bird>
    <barrier x="1155" y="660" type="ice" class="straight-01" rotation="90" ></barrier>
    <barrier x="1345" y="660" type="ice" class="straight-01" rotation="90" ></barrier>
    <barrier x="1250" y="545" type="ice" class="straight-01" rotation="0" ></barrier>
    <barrier x="1310" y="735" type="ice" class="straight-03" rotation="0" ></barrier>
    <barrier x="1280" y="675" type="wood" class="straight-03" rotation="90" ></barrier>
    <barrier x="1340" y="675" type="wood" class="straight-03" rotation="90" ></barrier>
    <barrier x="1310" y="625" type="wood" class="straight-03" rotation="0" ></barrier>
    <barrier x="1290" y="425" type="stone" class="straight-01" rotation="90" ></barrier>
    <barrier x="1210" y="425" type="stone" class="straight-01" rotation="90" ></barrier>
    <barrier x="1310" y="295" type="wood" class="straight-03" rotation="0" ></barrier>
    <barrier x="1100" y="675" type="wood" class="straight-03" rotation="90" ></barrier>
    <barrier x="1520" y="675" type="wood" class="straight-03" rotation="90" ></barrier>    
    <pig x="1330" y="440" type="small" rotation="0" ></pig>
  <!--   <pig x="1480" y="441" type="king" rotation="0" ></pig> -->
    <next-level worldId="2" stageId="1" levelId="3" ></next-level>
</level>